OpenAFSLibrary/__init__.py
OpenAFSLibrary/__version__.py
OpenAFSLibrary/command.py
OpenAFSLibrary/variable.py
OpenAFSLibrary/keywords/__init__.py
OpenAFSLibrary/keywords/acl.py
OpenAFSLibrary/keywords/cache.py
OpenAFSLibrary/keywords/command.py
OpenAFSLibrary/keywords/dump.py
OpenAFSLibrary/keywords/login.py
OpenAFSLibrary/keywords/pag.py
OpenAFSLibrary/keywords/path.py
OpenAFSLibrary/keywords/rx.py
OpenAFSLibrary/keywords/volume.py
robotframework_openafslibrary-1.0.0.dist-info/licenses/LICENSE
robotframework_openafslibrary-1.0.0.dist-info/METADATA
robotframework_openafslibrary-1.0.0.dist-info/WHEEL
robotframework_openafslibrary-1.0.0.dist-info/top_level.txt
robotframework_openafslibrary-1.0.0.dist-info/RECORD
