Metadata-Version: 2.4
Name: robotframework_openafslibrary
Version: 1.0.0
Summary: Robot Framework test library for OpenAFS
Home-page: https://github.com/openafs-contrib/robotframework-openafslibrary
Author: Michael Meffie
Author-email: mmeffie@sinenomine.net
License: BSD
Classifier: Development Status :: 4 - Beta
Classifier: Environment :: Console
Classifier: Intended Audience :: Developers
Classifier: License :: OSI Approved :: BSD License
Classifier: Operating System :: POSIX
Classifier: Programming Language :: Python :: 2.7
Classifier: Programming Language :: Python :: 3
Classifier: Topic :: Software Development
License-File: LICENSE
Requires-Dist: robotframework>=2.7.0
Dynamic: author
Dynamic: author-email
Dynamic: classifier
Dynamic: description
Dynamic: home-page
Dynamic: license
Dynamic: license-file
Dynamic: requires-dist
Dynamic: summary
